{
  "annotations": {
    "list": [
      {
        "builtIn": 1,
        "datasource": {
          "type": "grafana",
          "uid": "-- Grafana --"
        },
        "enable": true,
        "hide": true,
        "iconColor": "rgba(0, 211, 255, 1)",
        "name": "Annotations & Alerts",
        "type": "dashboard"
      }
    ]
  },
  "editable": true,
  "fiscalYearStartMonth": 0,
  "graphTooltip": 0,
  "id": 1,
  "links": [],
  "panels": [
    {
      "datasource": {
        "type": "prometheus",
        "uid": "de3mqczntvdogb"
      },
      "fieldConfig": {
        "defaults": {
          "color": {
            "mode": "palette-classic"
          },
          "custom": {
            "axisBorderShow": false,
            "axisCenteredZero": false,
            "axisColorMode": "text",
            "axisLabel": "",
            "axisPlacement": "auto",
            "barAlignment": 0,
            "barWidthFactor": 0.6,
            "drawStyle": "line",
            "fillOpacity": 0,
            "gradientMode": "none",
            "hideFrom": {
              "legend": false,
              "tooltip": false,
              "viz": false
            },
            "insertNulls": false,
            "lineInterpolation": "linear",
            "lineWidth": 1,
            "pointSize": 5,
            "scaleDistribution": {
              "type": "linear"
            },
            "showPoints": "auto",
            "spanNulls": false,
            "stacking": {
              "group": "A",
              "mode": "none"
            },
            "thresholdsStyle": {
              "mode": "off"
            }
          },
          "mappings": [],
          "thresholds": {
            "mode": "absolute",
            "steps": [
              {
                "color": "green",
                "value": null
              },
              {
                "color": "red",
                "value": 80
              }
            ]
          }
        },
        "overrides": []
      },
      "gridPos": {
        "h": 8,
        "w": 24,
        "x": 0,
        "y": 0
      },
      "id": 1,
      "options": {
        "legend": {
          "calcs": [],
          "displayMode": "list",
          "placement": "bottom",
          "showLegend": true
        },
        "tooltip": {
          "mode": "single",
          "sort": "none"
        }
      },
      "pluginVersion": "11.3.0",
      "targets": [
        {
          "datasource": {
            "type": "prometheus",
            "uid": "de3mqczntvdogb"
          },
          "disableTextWrap": false,
          "editorMode": "builder",
          "expr": "cpu_percentage{node=\"$host\"}",
          "fullMetaSearch": false,
          "includeNullMetadata": true,
          "legendFormat": "cpu usage",
          "range": true,
          "refId": "A",
          "useBackend": false
        }
      ],
      "title": "cpu usage",
      "type": "timeseries"
    }
  ],
  "preload": false,
  "schemaVersion": 40,
  "tags": [],
  "templating": {
    "list": [
      {
        "current": {
          "text": "raspi4",
          "value": "raspi4"
        },
        "definition": "label_values(node)",
        "name": "host",
        "options": [],
        "query": {
          "qryType": 1,
          "query": "label_values(node)",
          "refId": "PrometheusVariableQueryEditor-VariableQuery"
        },
        "refresh": 1,
        "regex": "",
        "type": "query"
      }
    ]
  },
  "time": {
    "from": "2024-11-11T14:26:29.382Z",
    "to": "2024-11-11T14:41:40.113Z"
  },
  "timepicker": {},
  "timezone": "browser",
  "title": "Monitoring",
  "uid": "ce3mqdz4uylmoa",
  "version": 4,
  "weekStart": ""
}